mjlab/__init__.py
mjlab/asset_zoo/README.md
mjlab/asset_zoo/__init__.py
mjlab/asset_zoo/img/g1.png
mjlab/asset_zoo/img/go1.png
mjlab/asset_zoo/render_robots.py
mjlab/asset_zoo/robots/__init__.py
mjlab/asset_zoo/robots/unitree_g1/__init__.py
mjlab/asset_zoo/robots/unitree_g1/g1_constants.py
mjlab/asset_zoo/robots/unitree_g1/xmls/assets/head_link.STL
mjlab/asset_zoo/robots/unitree_g1/xmls/assets/left_ankle_pitch_link.STL
mjlab/asset_zoo/robots/unitree_g1/xmls/assets/left_ankle_roll_link.STL
mjlab/asset_zoo/robots/unitree_g1/xmls/assets/left_elbow_link.STL
mjlab/asset_zoo/robots/unitree_g1/xmls/assets/left_hand_index_0_link.STL
mjlab/asset_zoo/robots/unitree_g1/xmls/assets/left_hand_index_1_link.STL
mjlab/asset_zoo/robots/unitree_g1/xmls/assets/left_hand_middle_0_link.STL
mjlab/asset_zoo/robots/unitree_g1/xmls/assets/left_hand_middle_1_link.STL
mjlab/asset_zoo/robots/unitree_g1/xmls/assets/left_hand_palm_link.STL
mjlab/asset_zoo/robots/unitree_g1/xmls/assets/left_hand_thumb_0_link.STL
mjlab/asset_zoo/robots/unitree_g1/xmls/assets/left_hand_thumb_1_link.STL
mjlab/asset_zoo/robots/unitree_g1/xmls/assets/left_hand_thumb_2_link.STL
mjlab/asset_zoo/robots/unitree_g1/xmls/assets/left_hip_pitch_link.STL
mjlab/asset_zoo/robots/unitree_g1/xmls/assets/left_hip_roll_link.STL
mjlab/asset_zoo/robots/unitree_g1/xmls/assets/left_hip_yaw_link.STL
mjlab/asset_zoo/robots/unitree_g1/xmls/assets/left_knee_link.STL
mjlab/asset_zoo/robots/unitree_g1/xmls/assets/left_rubber_hand.STL
mjlab/asset_zoo/robots/unitree_g1/xmls/assets/left_shoulder_pitch_link.STL
mjlab/asset_zoo/robots/unitree_g1/xmls/assets/left_shoulder_roll_link.STL
mjlab/asset_zoo/robots/unitree_g1/xmls/assets/left_shoulder_yaw_link.STL
mjlab/asset_zoo/robots/unitree_g1/xmls/assets/left_wrist_pitch_link.STL
mjlab/asset_zoo/robots/unitree_g1/xmls/assets/left_wrist_roll_link.STL
mjlab/asset_zoo/robots/unitree_g1/xmls/assets/left_wrist_yaw_link.STL
mjlab/asset_zoo/robots/unitree_g1/xmls/assets/logo_link.STL
mjlab-0.1.0.dist-info/licenses/LICENSE
mjlab-0.1.0.dist-info/licenses/src/mjlab/third_party/isaaclab/LICENSE
mjlab-0.1.0.dist-info/WHEEL
mjlab-0.1.0.dist-info/entry_points.txt
mjlab-0.1.0.dist-info/METADATA
mjlab-0.1.0.dist-info/RECORD
