Metadata-Version: 2.4
Name: mjlab
Version: 0.1.0
Summary: IsaacLab-style manager API, powered by MuJoCo-Warp, for RL and robotics research.
Keywords: mujoco,mujoco-warp,simulation,reinforcement-learning,robotics
Author: The MjLab Developers
License-Expression: Apache-2.0
License-File: LICENSE
License-File: src/mjlab/third_party/isaaclab/LICENSE
Classifier: Development Status :: 4 - Beta
Classifier: Intended Audience :: Developers
Classifier: Intended Audience :: Science/Research
Classifier: License :: OSI Approved :: Apache Software License
Classifier: Programming Language :: Python :: 3
Classifier: Programming Language :: Python :: 3.10
Classifier: Programming Language :: Python :: 3.11
Classifier: Programming Language :: Python :: 3.12
Classifier: Programming Language :: Python :: 3.13
Classifier: Programming Language :: Python :: 3 :: Only
Classifier: Typing :: Typed
Classifier: Environment :: GPU :: NVIDIA CUDA
Classifier: Topic :: Scientific/Engineering
Classifier: Natural Language :: English
Requires-Dist: gymnasium==1.2.0
Requires-Dist: prettytable
Requires-Dist: tqdm
Requires-Dist: tyro
Requires-Dist: torch
Requires-Dist: warp-lang
Requires-Dist: mujoco-warp
Requires-Dist: mujoco
Requires-Dist: trimesh
Requires-Dist: viser
Requires-Dist: wandb
Requires-Dist: moviepy
Requires-Dist: tensordict
Requires-Dist: rsl-rl-lib
Requires-Dist: tensorboard>=2.20.0
Requires-Dist: torch>=2.7.0 ; extra == 'cu12'
Requires-Python: >=3.10, <3.14
Project-URL: Bug Reports, https://github.com/mujocolab/mjlab/issues
Project-URL: Source, https://github.com/mujocolab/mjlab
Provides-Extra: cu12
